labeledclusters/__init__.py
labeledclusters/clusters.py
labeledclusters/labeledclusters.py
labeledclusters-0.0.3.dist-info/LICENSE
labeledclusters-0.0.3.dist-info/METADATA
labeledclusters-0.0.3.dist-info/WHEEL
labeledclusters-0.0.3.dist-info/top_level.txt
labeledclusters-0.0.3.dist-info/RECORD
